Workbook

Sheet Summary
A1: OLD GALVEZ MHP | C1: 2025 YTD
B2: JAN | C2: FEB | D2: MAR | E2: APR | F2: MAY | G2: JUN | H2: JUL | I2: AUG | J2: SEPT | K2: OCT | L2: NOV | M2: DEC | N2: TOTALS
A3: Income | B3: =Income!B36 -> 33130.66 | C3: =Income!C36 -> 30289.75 | D3: =Income!D36 -> 35149.55 | E3: =Income!E36 -> 32338.09 | F3: =Income!F36 -> 30018.6 | G3: =Income!G36 -> 27991.57 | H3: =Income!H36 -> 26863.47 | I3: =Income!I36 -> 23916.91 | ... M3: =Income!M36 -> 30592.5 | N3: =SUM(B3:M3) -> 351739.73
A4: Maintenance | B4: 1329 | C4: 3527 | D4: 2860 | E4: 2062 | F4: 4518 | G4: 3606 | H4: 3133 | I4: 1843 | J4: 3483 | K4: 3020 | L4: 2744 | M4: 763.77 | N4: =SUM(B4:M4) -> 32888.77
A5: Electricity | B5: 536.87 | C5: 489.89 | D5: 509.3 | E5: 652 | F5: 510.24 | G5: 501.05 | H5: 516.17 | I5: 524.52 | J5: 496.66 | K5: 489.89 | L5: 480 | M5: 469.52 | N5: =SUM(B5:M5) -> 6176.11
A6: Insurance | B6: 1577.73 | C6: 1577.73 | D6: 1577.73 | E6: 1577.73 | F6: 1577.73 | G6: 1577.73 | H6: 1577.73 | I6: 1577.73 | J6: 1577.73 | K6: 1577.73 | L6: 1577.73 | M6: 1577.73 | N6: =SUM(B6:M6) -> 18932.76
A7: Trash | B7: 328 | C7: 328 | D7: 328 | E7: 328 | F7: 328 | G7: 328 | H7: 328 | I7: 328 | J7: 328 | K7: 328 | L7: 328 | M7: 328 | N7: =SUM(B7:M7) -> 3936
A8: Lawn Care | B8: 0 | E8: 300 | F8: 300 | G8: 300 | H8: 300 | I8: 300 | J8: 300 | K8: 300 | N8: =SUM(B8:M8) -> 2100
A9: Waste Water Sol | B9: 250 | C9: 250 | D9: 250 | E9: 250 | F9: 250 | G9: 250 | H9: 250 | I9: 250 | J9: 250 | K9: 250 | L9: 250 | M9: 250 | N9: =SUM(B9:M9) -> 3000
A10: Management
A11: Property Tax
A14: Net | B14: =B3-B4-B5-B6-B7-B8-B9 -> 29109.06 | C14: =C3-C4-C5-C6-C7-C8-C9 -> 24117.13 | D14: =D3-D4-D5-D6-D7-D8-D9 -> 29624.52 | E14: =E3-E4-E5-E6-E7-E8-E9 -> 27168.36 | F14: =F3-F4-F5-F6-F7-F8-F9 -> 22534.63 | G14: =G3-G4-G5-G6-G7-G8-G9 -> 21428.79 | H14: =H3-H4-H5-H6-H7-H8-H9 -> 20758.57 | I14: =I3-I4-I5-I6-I7-I8-I9 -> 19093.66 | ... M14: =M3-M4-M5-M6-M7-M8-M9 -> 27203.48 | N14: =SUM(B14:M14) -> 284706.09

Sheet Income
A1: OLD GALVEZ MHP rent income | C1: 2025 YTD
A2: Unit | B2: JAN | C2: FEB | D2: MAR | E2: APR | F2: MAY | G2: JUN | H2: JUL | I2: AUG | J2: SEPT | K2: OCT | L2: NOV | M2: DEC | O2: Beds | P2: Baths | Q2: Year Model
A3: 1 | B3: 1250 | C3: 1250 | D3: 1300 | E3: 1250 | F3: 1250 | G3: 1250 | J3: 1300 | K3: 1300 | L3: 1300 | M3: 1300 | O3: 3 | P3: 2 | Q3: 2018
A4: 2 | B4: 1250 | G4: 1593.58 | H4: 1300 | I4: 1300 | J4: 1300 | K4: 1300 | L4: 1300 | M4: 1300 | O4: 3 | P4: 2 | Q4: 2018
A5: 3 | B5: 1250 | C5: 1250 | D5: 1300 | E5: 1300 | F5: 1300 | G5: 900 | H5: 1290 | I5: 950 | J5: 0 | M5: 1300 | O5: 3 | P5: 2 | Q5: 2018
A6: 4 | B6: 350 | C6: 350 | D6: 425 | E6: 425 | F6: 425 | G6: 425 | H6: 425 | I6: 425 | J6: 425 | K6: 425 | L6: 425 | M6: 425 | O6: Lot Rent
A7: 5 | I7: 419.35 | J7: 1300 | K7: 750 | O7: 3 | P7: 2 | Q7: 2018
A8: 6 | B8: 1250 | C8: 1250 | D8: 1250 | E8: 1250 | F8: 1250 | G8: 1250 | H8: 1250 | J8: 1250 | K8: 1250 | L8: 1250 | M8: 675 | O8: 3 | P8: 2 | Q8: 2018
A9: 7 | B9: 1250 | C9: 1250 | D9: 1250 | E9: 1250 | F9: 950 | O9: 3 | P9: 2 | Q9: 2018
A10: 8 | B10: 950 | C10: 1250 | D10: 1300 | E10: 1250 | F10: 1250 | G10: 1300 | H10: 1300 | I10: 1300 | J10: 1250 | K10: 1300 | L10: 1300 | M10: 1142.5 | O10: 3 | P10: 2 | Q10: 2018
A11: 9 | B11: 350 | C11: 350 | D11: 425 | E11: 425 | F11: 425 | G11: 425 | I11: 425 | J11: 425 | K11: 425 | L11: 425 | M11: 425 | O11: Lot Rent
A12: 10 | B12: 1250 | C12: 1250 | E12: 1120 | H12: 587.16 | I12: 1300 | K12: 629.03 | L12: 1300 | M12: 1300 | O12: 3 | P12: 2 | Q12: 2018
A13: 11 | B13: 1050 | C13: 1250 | E13: 1250 | J13: 1300 | K13: 1300 | L13: 1300 | M13: 1300 | O13: 3 | P13: 2 | Q13: 2018
A14: 12 | B14: 1250 | C14: 1250 | D14: 1250 | E14: 1250 | F14: 1250 | G14: 1240 | H14: 1250 | J14: 1250 | K14: 1200 | L14: 1250 | M14: 1200 | O14: 3 | P14: 2 | Q14: 2018
A15: 13 | B15: 1250 | C15: 1300 | D15: 975 | F15: 500 | I15: 1300 | J15: 1300 | K15: 1300 | L15: 1300 | M15: 1140 | O15: 3 | P15: 2 | Q15: 2018
A16: 14 | B16: 300 | C16: 1250 | D16: 1250 | E16: 1250 | F16: 1250 | G16: 1250 | H16: 1250 | I16: 1250 | J16: 1250 | K16: 1250 | L16: 1250 | M16: 1250 | O16: 3 | P16: 2 | Q16: 2018
A17: 15 | B17: 350 | C17: 350 | D17: 425 | E17: 425 | F17: 425 | G17: 425 | H17: 425 | I17: 425 | J17: 425 | K17: 425 | L17: 425 | M17: 425 | O17: Lot Rent
A18: 16 | B18: 1250 | C18: 1250 | D18: 1250 | E18: 1250 | F18: 1250 | G18: 1250 | J18: 1300 | K18: 1300 | L18: 1300 | M18: 1300 | O18: 3 | P18: 2 | Q18: 2018
A19: 17 | D19: 1300 | E19: 1654 | F19: 859 | G19: 1841 | H19: 1350 | I19: 1200 | J19: 1300 | K19: 1300 | L19: 875 | M19: 1725 | O19: 3 | P19: 2 | Q19: 2018
A20: 18 | B20: 800 | C20: 900 | D20: 1550 | E20: 1250 | F20: 950 | G20: 1650 | H20: 950 | I20: 1550 | J20: 800 | K20: 1250 | L20: 1250 | M20: 850 | O20: 3 | P20: 2 | Q20: 2018
A21: 19 | H21: 970 | I21: 1200 | J21: 1000 | L21: 1083 | M21: 205 | O21: 3 | P21: 2 | Q21: 2018
A22: 20 | G22: 1083.33 | H22: 1350 | I22: 1300 | J22: 1300 | K22: 1300 | L22: 1300 | M22: 1300 | O22: 3 | P22: 2 | Q22: 2018
A23: 21 | B23: 1250 | C23: 1250 | D23: 1250 | E23: 1250 | F23: 1250 | G23: 1250 | H23: 1250 | I23: 1250 | J23: 1250 | K23: 1250 | L23: 1250 | M23: 1250 | O23: 3 | P23: 2 | Q23: 2018
A24: 22 | D24: 1250 | E24: 1250 | F24: 1300 | G24: 434.98 | H24: 1947 | I24: 1152.56 | J24: 1250 | K24: 1250 | L24: 1250 | M24: 1250 | O24: 3 | P24: 2 | Q24: 2018
A25: 23 | B25: 1250 | C25: 1234 | D25: 1316 | E25: 1042 | F25: 1108 | G25: 1425 | L25: 1300 | M25: 1300 | O25: 3 | P25: 2 | Q25: 2018
A26: 24 | B26: 1250 | C26: 1250 | D26: 1250 | E26: 1250 | F26: 1250 | G26: 1250 | H26: 1250 | I26: 1250 | K26: 630 | L26: 1300 | M26: 1300 | O26: 3 | P26: 2 | Q26: 2018
A27: 25 | B27: 1250 | C27: 1200 | D27: 1250 | E27: 1250 | F27: 800 | G27: 750 | H27: 1600 | I27: 620 | J27: 397.5 | K27: 650 | L27: 1200 | M27: 830 | O27: 3 | P27: 2 | Q27: 2018
A28: 26 | B28: 1250 | C28: 1250 | D28: 1250 | E28: 500 | F28: 1300 | G28: 1300 | H28: 1300 | I28: 1300 | J28: 1300 | K28: 1300 | L28: 1300 | M28: 1250 | O28: 3 | P28: 2 | Q28: 2018
A29: 27 | B29: 1250 | C29: 1250 | D29: 1250 | E29: 1250 | F29: 1250 | G29: 1300 | I29: 1300 | L29: 780 | M29: 1300 | O29: 3 | P29: 2 | Q29: 2018
A30: 28 | B30: 1250 | C30: 550 | D30: 1300 | E30: 1300 | F30: 1300 | H30: 1300 | I30: 400 | K30: 629.1 | L30: 1300 | M30: 1300 | O30: 3 | P30: 2 | Q30: 2018
A31: 29 | B31: 1250 | C31: 1250 | D31: 1300 | E31: 1300 | F31: 1300 | G31: 1300 | H31: 1300 | I31: 1350 | J31: 1300 | K31: 1300 | L31: 1300 | M31: 1300 | O31: 3 | P31: 2 | Q31: 2018
A32: 30 | B32: 950 | C32: 950 | D32: 950 | E32: 950 | F32: 950 | G32: 950 | H32: 950 | I32: 950 | J32: 950 | K32: 950 | L32: 950 | M32: 950 | O32: 2 | P32: 1 | Q32: 2018
A34: air bnb (2,5,19, &20) | B34: 6780.66 | C34: 4355.75 | D34: 7533.55 | E34: 4397.09 | F34: 4876.6 | G34: 2148.68 | H34: 2269.31 | I34: 0 | J34: 0 | K34: 0 | O34: Air B&B terminated August 2025
B36: =SUM(B3:B35) -> 33130.66 | C36: =SUM(C3:C35) -> 30289.75 | D36: =SUM(D3:D35) -> 35149.55 | E36: =SUM(E3:E35) -> 32338.09 | F36: =SUM(F3:F35) -> 30018.6 | G36: =SUM(G3:G35) -> 27991.57 | H36: =SUM(H3:H35) -> 26863.47 | I36: =SUM(I3:I35) -> 23916.91 | ... M36: =SUM(M3:M35) -> 30592.5 | O36: =SUM(B36:N36) -> 351739.73 | P36: TOTAL
A39: 2026 Scheduled Gross Income | B39: 413904
A41: 2025 Expenses
A42: Property Tax | B42: -9023
A43: Hazard & Liability Ins | B43: -23058
A44: Flood Ins | B44: -15606
A45: Mnagement @ 7% | B45: -29000
A46: Electric | B46: -6176 | C46: Treatment plant power only 2026. 2025 included Air B&B rentals
A47: Trash | B47: -3936
A48: Private Sewer Treatment Plant | B48: -3000
A49: City Water | B49: 0
A50: Lawn Care | B50: -4000
A51: Maintenance @5% | B51: -20695
A54: Scheduled NOI | B54: =SUM(B39:B53) -> 299410
A58: 2026 Actual Gross Income | B58: 372000
A60: 2025 Expenses
A61: Property Tax | B61: -9023
A62: Hazard & Liability Ins | B62: -23058
A63: Flood Ins | B63: -15606
A64: Mnagement @ 7% | B64: -29000
A65: Electric | B65: -1200 | C65: Adjusted for 2026 No Air B&B
A66: Trash | B66: -3936
A67: Private Sewer Treatment Plant | B67: -3000
A68: City Water | B68: 0
A69: Lawn Care | B69: -4000
A70: Maintenance @5% | B70: -20695
A73: Actual NOI | B73: =SUM(B58:B72) -> 262482
A74: Actual CAP | B74: 8.7
